{
  "version": "tree-0.1",
  "tree": {
    "id": "App",
    "path": "",
    "children": {
      "ProductService": {
        "id": "ProductService",
        "path": "ProductService",
        "children": {
          "listProducts": {
            "id": "listProducts",
            "path": "ProductService/listProducts",
            "children": {
              "ServiceRole": {
                "id": "ServiceRole",
                "path": "ProductService/listProducts/ServiceRole",
                "children": {
                  "ImportServiceRole": {
                    "id": "ImportServiceRole",
                    "path": "ProductService/listProducts/ServiceRole/ImportServiceRole",
                    "constructInfo": {
                      "fqn": "aws-cdk-lib.Resource",
                      "version": "2.147.1"
                    }
                  },
                  "Resource": {
                    "id": "Resource",
                    "path": "ProductService/listProducts/ServiceRole/Resource",
                    "attributes": {
                      "aws:cdk:cloudformation:type": "AWS::IAM::Role",
                      "aws:cdk:cloudformation:props": {
                        "assumeRolePolicyDocument": {
                          "Statement": [
                            {
                              "Action": "sts:AssumeRole",
                              "Effect": "Allow",
                              "Principal": {
                                "Service": "lambda.amazonaws.com"
                              }
                            }
                          ],
                          "Version": "2012-10-17"
                        },
                        "managedPolicyArns": [
                          {
                            "Fn::Join": [
                              "",
                              [
                                "arn:",
                                {
                                  "Ref": "AWS::Partition"
                                },
                                ":iam::aws:policy/service-role/AWSLambdaBasicExecutionRole"
                              ]
                            ]
                          }
                        ]
                      }
                    },
                    "constructInfo": {
                      "fqn": "aws-cdk-lib.aws_iam.CfnRole",
                      "version": "2.147.1"
                    }
                  },
                  "DefaultPolicy": {
                    "id": "DefaultPolicy",
                    "path": "ProductService/listProducts/ServiceRole/DefaultPolicy",
                    "children": {
                      "Resource": {
                        "id": "Resource",
                        "path": "ProductService/listProducts/ServiceRole/DefaultPolicy/Resource",
                        "attributes": {
                          "aws:cdk:cloudformation:type": "AWS::IAM::Policy",
                          "aws:cdk:cloudformation:props": {
                            "policyDocument": {
                              "Statement": [
                                {
                                  "Action": [
                                    "dynamodb:GetItem",
                                    "dynamodb:PutItem",
                                    "dynamodb:Query",
                                    "dynamodb:Scan",
                                    "dynamodb:UpdateItem"
                                  ],
                                  "Effect": "Allow",
                                  "Resource": [
                                    "arn:aws:dynamodb:eu-central-1:590184139356:table/Product",
                                    "arn:aws:dynamodb:eu-central-1:590184139356:table/Stock"
                                  ]
                                }
                              ],
                              "Version": "2012-10-17"
                            },
                            "policyName": "listProductsServiceRoleDefaultPolicyC06B5225",
                            "roles": [
                              {
                                "Ref": "listProductsServiceRole1ADC593D"
                              }
                            ]
                          }
                        },
                        "constructInfo": {
                          "fqn": "aws-cdk-lib.aws_iam.CfnPolicy",
                          "version": "2.147.1"
                        }
                      }
                    },
                    "constructInfo": {
                      "fqn": "aws-cdk-lib.aws_iam.Policy",
                      "version": "2.147.1"
                    }
                  }
                },
                "constructInfo": {
                  "fqn": "aws-cdk-lib.aws_iam.Role",
                  "version": "2.147.1"
                }
              },
              "Code": {
                "id": "Code",
                "path": "ProductService/listProducts/Code",
                "children": {
                  "Stage": {
                    "id": "Stage",
                    "path": "ProductService/listProducts/Code/Stage",
                    "constructInfo": {
                      "fqn": "aws-cdk-lib.AssetStaging",
                      "version": "2.147.1"
                    }
                  },
                  "AssetBucket": {
                    "id": "AssetBucket",
                    "path": "ProductService/listProducts/Code/AssetBucket",
                    "constructInfo": {
                      "fqn": "aws-cdk-lib.aws_s3.BucketBase",
                      "version": "2.147.1"
                    }
                  }
                },
                "constructInfo": {
                  "fqn": "aws-cdk-lib.aws_s3_assets.Asset",
                  "version": "2.147.1"
                }
              },
              "Resource": {
                "id": "Resource",
                "path": "ProductService/listProducts/Resource",
                "attributes": {
                  "aws:cdk:cloudformation:type": "AWS::Lambda::Function",
                  "aws:cdk:cloudformation:props": {
                    "code": {
                      "s3Bucket": {
                        "Fn::Sub": "cdk-hnb659fds-assets-${AWS::AccountId}-${AWS::Region}"
                      },
                      "s3Key": "59bc3263b242c16db6ae85b38b58f560b10b797f32c32bd37f0cd1cb4b055c5e.zip"
                    },
                    "environment": {
                      "variables": {
                        "PRODUCTS_TABLE_NAME": "Product",
                        "STOCKS_TABLE_NAME": "Stock"
                      }
                    },
                    "handler": "getProductsList.handler",
                    "role": {
                      "Fn::GetAtt": [
                        "listProductsServiceRole1ADC593D",
                        "Arn"
                      ]
                    },
                    "runtime": "nodejs20.x"
                  }
                },
                "constructInfo": {
                  "fqn": "aws-cdk-lib.aws_lambda.CfnFunction",
                  "version": "2.147.1"
                }
              }
            },
            "constructInfo": {
              "fqn": "aws-cdk-lib.aws_lambda.Function",
              "version": "2.147.1"
            }
          },
          "createProduct": {
            "id": "createProduct",
            "path": "ProductService/createProduct",
            "children": {
              "ServiceRole": {
                "id": "ServiceRole",
                "path": "ProductService/createProduct/ServiceRole",
                "children": {
                  "ImportServiceRole": {
                    "id": "ImportServiceRole",
                    "path": "ProductService/createProduct/ServiceRole/ImportServiceRole",
                    "constructInfo": {
                      "fqn": "aws-cdk-lib.Resource",
                      "version": "2.147.1"
                    }
                  },
                  "Resource": {
                    "id": "Resource",
                    "path": "ProductService/createProduct/ServiceRole/Resource",
                    "attributes": {
                      "aws:cdk:cloudformation:type": "AWS::IAM::Role",
                      "aws:cdk:cloudformation:props": {
                        "assumeRolePolicyDocument": {
                          "Statement": [
                            {
                              "Action": "sts:AssumeRole",
                              "Effect": "Allow",
                              "Principal": {
                                "Service": "lambda.amazonaws.com"
                              }
                            }
                          ],
                          "Version": "2012-10-17"
                        },
                        "managedPolicyArns": [
                          {
                            "Fn::Join": [
                              "",
                              [
                                "arn:",
                                {
                                  "Ref": "AWS::Partition"
                                },
                                ":iam::aws:policy/service-role/AWSLambdaBasicExecutionRole"
                              ]
                            ]
                          }
                        ]
                      }
                    },
                    "constructInfo": {
                      "fqn": "aws-cdk-lib.aws_iam.CfnRole",
                      "version": "2.147.1"
                    }
                  },
                  "DefaultPolicy": {
                    "id": "DefaultPolicy",
                    "path": "ProductService/createProduct/ServiceRole/DefaultPolicy",
                    "children": {
                      "Resource": {
                        "id": "Resource",
                        "path": "ProductService/createProduct/ServiceRole/DefaultPolicy/Resource",
                        "attributes": {
                          "aws:cdk:cloudformation:type": "AWS::IAM::Policy",
                          "aws:cdk:cloudformation:props": {
                            "policyDocument": {
                              "Statement": [
                                {
                                  "Action": [
                                    "dynamodb:GetItem",
                                    "dynamodb:PutItem",
                                    "dynamodb:Query",
                                    "dynamodb:Scan",
                                    "dynamodb:UpdateItem"
                                  ],
                                  "Effect": "Allow",
                                  "Resource": [
                                    "arn:aws:dynamodb:eu-central-1:590184139356:table/Product",
                                    "arn:aws:dynamodb:eu-central-1:590184139356:table/Stock"
                                  ]
                                }
                              ],
                              "Version": "2012-10-17"
                            },
                            "policyName": "createProductServiceRoleDefaultPolicyA4987AF8",
                            "roles": [
                              {
                                "Ref": "createProductServiceRole49F078DF"
                              }
                            ]
                          }
                        },
                        "constructInfo": {
                          "fqn": "aws-cdk-lib.aws_iam.CfnPolicy",
                          "version": "2.147.1"
                        }
                      }
                    },
                    "constructInfo": {
                      "fqn": "aws-cdk-lib.aws_iam.Policy",
                      "version": "2.147.1"
                    }
                  }
                },
                "constructInfo": {
                  "fqn": "aws-cdk-lib.aws_iam.Role",
                  "version": "2.147.1"
                }
              },
              "Code": {
                "id": "Code",
                "path": "ProductService/createProduct/Code",
                "children": {
                  "Stage": {
                    "id": "Stage",
                    "path": "ProductService/createProduct/Code/Stage",
                    "constructInfo": {
                      "fqn": "aws-cdk-lib.AssetStaging",
                      "version": "2.147.1"
                    }
                  },
                  "AssetBucket": {
                    "id": "AssetBucket",
                    "path": "ProductService/createProduct/Code/AssetBucket",
                    "constructInfo": {
                      "fqn": "aws-cdk-lib.aws_s3.BucketBase",
                      "version": "2.147.1"
                    }
                  }
                },
                "constructInfo": {
                  "fqn": "aws-cdk-lib.aws_s3_assets.Asset",
                  "version": "2.147.1"
                }
              },
              "Resource": {
                "id": "Resource",
                "path": "ProductService/createProduct/Resource",
                "attributes": {
                  "aws:cdk:cloudformation:type": "AWS::Lambda::Function",
                  "aws:cdk:cloudformation:props": {
                    "code": {
                      "s3Bucket": {
                        "Fn::Sub": "cdk-hnb659fds-assets-${AWS::AccountId}-${AWS::Region}"
                      },
                      "s3Key": "59bc3263b242c16db6ae85b38b58f560b10b797f32c32bd37f0cd1cb4b055c5e.zip"
                    },
                    "environment": {
                      "variables": {
                        "PRODUCTS_TABLE_NAME": "Product",
                        "STOCKS_TABLE_NAME": "Stock"
                      }
                    },
                    "handler": "createProduct.handler",
                    "role": {
                      "Fn::GetAtt": [
                        "createProductServiceRole49F078DF",
                        "Arn"
                      ]
                    },
                    "runtime": "nodejs20.x"
                  }
                },
                "constructInfo": {
                  "fqn": "aws-cdk-lib.aws_lambda.CfnFunction",
                  "version": "2.147.1"
                }
              }
            },
            "constructInfo": {
              "fqn": "aws-cdk-lib.aws_lambda.Function",
              "version": "2.147.1"
            }
          },
          "getProductById": {
            "id": "getProductById",
            "path": "ProductService/getProductById",
            "children": {
              "ServiceRole": {
                "id": "ServiceRole",
                "path": "ProductService/getProductById/ServiceRole",
                "children": {
                  "ImportServiceRole": {
                    "id": "ImportServiceRole",
                    "path": "ProductService/getProductById/ServiceRole/ImportServiceRole",
                    "constructInfo": {
                      "fqn": "aws-cdk-lib.Resource",
                      "version": "2.147.1"
                    }
                  },
                  "Resource": {
                    "id": "Resource",
                    "path": "ProductService/getProductById/ServiceRole/Resource",
                    "attributes": {
                      "aws:cdk:cloudformation:type": "AWS::IAM::Role",
                      "aws:cdk:cloudformation:props": {
                        "assumeRolePolicyDocument": {
                          "Statement": [
                            {
                              "Action": "sts:AssumeRole",
                              "Effect": "Allow",
                              "Principal": {
                                "Service": "lambda.amazonaws.com"
                              }
                            }
                          ],
                          "Version": "2012-10-17"
                        },
                        "managedPolicyArns": [
                          {
                            "Fn::Join": [
                              "",
                              [
                                "arn:",
                                {
                                  "Ref": "AWS::Partition"
                                },
                                ":iam::aws:policy/service-role/AWSLambdaBasicExecutionRole"
                              ]
                            ]
                          }
                        ]
                      }
                    },
                    "constructInfo": {
                      "fqn": "aws-cdk-lib.aws_iam.CfnRole",
                      "version": "2.147.1"
                    }
                  },
                  "DefaultPolicy": {
                    "id": "DefaultPolicy",
                    "path": "ProductService/getProductById/ServiceRole/DefaultPolicy",
                    "children": {
                      "Resource": {
                        "id": "Resource",
                        "path": "ProductService/getProductById/ServiceRole/DefaultPolicy/Resource",
                        "attributes": {
                          "aws:cdk:cloudformation:type": "AWS::IAM::Policy",
                          "aws:cdk:cloudformation:props": {
                            "policyDocument": {
                              "Statement": [
                                {
                                  "Action": [
                                    "dynamodb:GetItem",
                                    "dynamodb:PutItem",
                                    "dynamodb:Query",
                                    "dynamodb:Scan",
                                    "dynamodb:UpdateItem"
                                  ],
                                  "Effect": "Allow",
                                  "Resource": [
                                    "arn:aws:dynamodb:eu-central-1:590184139356:table/Product",
                                    "arn:aws:dynamodb:eu-central-1:590184139356:table/Stock"
                                  ]
                                }
                              ],
                              "Version": "2012-10-17"
                            },
                            "policyName": "getProductByIdServiceRoleDefaultPolicy342C5F05",
                            "roles": [
                              {
                                "Ref": "getProductByIdServiceRoleB7E5A825"
                              }
                            ]
                          }
                        },
                        "constructInfo": {
                          "fqn": "aws-cdk-lib.aws_iam.CfnPolicy",
                          "version": "2.147.1"
                        }
                      }
                    },
                    "constructInfo": {
                      "fqn": "aws-cdk-lib.aws_iam.Policy",
                      "version": "2.147.1"
                    }
                  }
                },
                "constructInfo": {
                  "fqn": "aws-cdk-lib.aws_iam.Role",
                  "version": "2.147.1"
                }
              },
              "Code": {
                "id": "Code",
                "path": "ProductService/getProductById/Code",
                "children": {
                  "Stage": {
                    "id": "Stage",
                    "path": "ProductService/getProductById/Code/Stage",
                    "constructInfo": {
                      "fqn": "aws-cdk-lib.AssetStaging",
                      "version": "2.147.1"
                    }
                  },
                  "AssetBucket": {
                    "id": "AssetBucket",
                    "path": "ProductService/getProductById/Code/AssetBucket",
                    "constructInfo": {
                      "fqn": "aws-cdk-lib.aws_s3.BucketBase",
                      "version": "2.147.1"
                    }
                  }
                },
                "constructInfo": {
                  "fqn": "aws-cdk-lib.aws_s3_assets.Asset",
                  "version": "2.147.1"
                }
              },
              "Resource": {
                "id": "Resource",
                "path": "ProductService/getProductById/Resource",
                "attributes": {
                  "aws:cdk:cloudformation:type": "AWS::Lambda::Function",
                  "aws:cdk:cloudformation:props": {
                    "code": {
                      "s3Bucket": {
                        "Fn::Sub": "cdk-hnb659fds-assets-${AWS::AccountId}-${AWS::Region}"
                      },
                      "s3Key": "59bc3263b242c16db6ae85b38b58f560b10b797f32c32bd37f0cd1cb4b055c5e.zip"
                    },
                    "environment": {
                      "variables": {
                        "PRODUCTS_TABLE_NAME": "Product",
                        "STOCKS_TABLE_NAME": "Stock"
                      }
                    },
                    "handler": "getProductById.handler",
                    "role": {
                      "Fn::GetAtt": [
                        "getProductByIdServiceRoleB7E5A825",
                        "Arn"
                      ]
                    },
                    "runtime": "nodejs20.x"
                  }
                },
                "constructInfo": {
                  "fqn": "aws-cdk-lib.aws_lambda.CfnFunction",
                  "version": "2.147.1"
                }
              }
            },
            "constructInfo": {
              "fqn": "aws-cdk-lib.aws_lambda.Function",
              "version": "2.147.1"
            }
          },
          "Api": {
            "id": "Api",
            "path": "ProductService/Api",
            "children": {
              "Resource": {
                "id": "Resource",
                "path": "ProductService/Api/Resource",
                "attributes": {
                  "aws:cdk:cloudformation:type": "AWS::ApiGatewayV2::Api",
                  "aws:cdk:cloudformation:props": {
                    "corsConfiguration": {
                      "allowHeaders": [
                        "*"
                      ],
                      "allowMethods": [
                        "GET",
                        "POST",
                        "OPTIONS"
                      ],
                      "allowOrigins": [
                        "*"
                      ]
                    },
                    "description": "products",
                    "name": "Api",
                    "protocolType": "HTTP"
                  }
                },
                "constructInfo": {
                  "fqn": "aws-cdk-lib.aws_apigatewayv2.CfnApi",
                  "version": "2.147.1"
                }
              },
              "DefaultStage": {
                "id": "DefaultStage",
                "path": "ProductService/Api/DefaultStage",
                "children": {
                  "Resource": {
                    "id": "Resource",
                    "path": "ProductService/Api/DefaultStage/Resource",
                    "attributes": {
                      "aws:cdk:cloudformation:type": "AWS::ApiGatewayV2::Stage",
                      "aws:cdk:cloudformation:props": {
                        "apiId": {
                          "Ref": "ApiF70053CD"
                        },
                        "autoDeploy": true,
                        "stageName": "$default"
                      }
                    },
                    "constructInfo": {
                      "fqn": "aws-cdk-lib.aws_apigatewayv2.CfnStage",
                      "version": "2.147.1"
                    }
                  }
                },
                "constructInfo": {
                  "fqn": "aws-cdk-lib.aws_apigatewayv2.HttpStage",
                  "version": "2.147.1"
                }
              },
              "GET--products": {
                "id": "GET--products",
                "path": "ProductService/Api/GET--products",
                "children": {
                  "getListProducts": {
                    "id": "getListProducts",
                    "path": "ProductService/Api/GET--products/getListProducts",
                    "children": {
                      "Resource": {
                        "id": "Resource",
                        "path": "ProductService/Api/GET--products/getListProducts/Resource",
                        "attributes": {
                          "aws:cdk:cloudformation:type": "AWS::ApiGatewayV2::Integration",
                          "aws:cdk:cloudformation:props": {
                            "apiId": {
                              "Ref": "ApiF70053CD"
                            },
                            "integrationType": "AWS_PROXY",
                            "integrationUri": {
                              "Fn::GetAtt": [
                                "listProducts10125CE9",
                                "Arn"
                              ]
                            },
                            "payloadFormatVersion": "2.0"
                          }
                        },
                        "constructInfo": {
                          "fqn": "aws-cdk-lib.aws_apigatewayv2.CfnIntegration",
                          "version": "2.147.1"
                        }
                      }
                    },
                    "constructInfo": {
                      "fqn": "aws-cdk-lib.aws_apigatewayv2.HttpIntegration",
                      "version": "2.147.1"
                    }
                  },
                  "getListProducts-Permission": {
                    "id": "getListProducts-Permission",
                    "path": "ProductService/Api/GET--products/getListProducts-Permission",
                    "attributes": {
                      "aws:cdk:cloudformation:type": "AWS::Lambda::Permission",
                      "aws:cdk:cloudformation:props": {
                        "action": "lambda:InvokeFunction",
                        "functionName": {
                          "Fn::GetAtt": [
                            "listProducts10125CE9",
                            "Arn"
                          ]
                        },
                        "principal": "apigateway.amazonaws.com",
                        "sourceArn": {
                          "Fn::Join": [
                            "",
                            [
                              "arn:",
                              {
                                "Ref": "AWS::Partition"
                              },
                              ":execute-api:",
                              {
                                "Ref": "AWS::Region"
                              },
                              ":",
                              {
                                "Ref": "AWS::AccountId"
                              },
                              ":",
                              {
                                "Ref": "ApiF70053CD"
                              },
                              "/*/*/products"
                            ]
                          ]
                        }
                      }
                    },
                    "constructInfo": {
                      "fqn": "aws-cdk-lib.aws_lambda.CfnPermission",
                      "version": "2.147.1"
                    }
                  },
                  "Resource": {
                    "id": "Resource",
                    "path": "ProductService/Api/GET--products/Resource",
                    "attributes": {
                      "aws:cdk:cloudformation:type": "AWS::ApiGatewayV2::Route",
                      "aws:cdk:cloudformation:props": {
                        "apiId": {
                          "Ref": "ApiF70053CD"
                        },
                        "authorizationType": "NONE",
                        "routeKey": "GET /products",
                        "target": {
                          "Fn::Join": [
                            "",
                            [
                              "integrations/",
                              {
                                "Ref": "ApiGETproductsgetListProducts68603C82"
                              }
                            ]
                          ]
                        }
                      }
                    },
                    "constructInfo": {
                      "fqn": "aws-cdk-lib.aws_apigatewayv2.CfnRoute",
                      "version": "2.147.1"
                    }
                  }
                },
                "constructInfo": {
                  "fqn": "aws-cdk-lib.aws_apigatewayv2.HttpRoute",
                  "version": "2.147.1"
                }
              },
              "GET--products--{id}": {
                "id": "GET--products--{id}",
                "path": "ProductService/Api/GET--products--{id}",
                "children": {
                  "GetByIdProducts": {
                    "id": "GetByIdProducts",
                    "path": "ProductService/Api/GET--products--{id}/GetByIdProducts",
                    "children": {
                      "Resource": {
                        "id": "Resource",
                        "path": "ProductService/Api/GET--products--{id}/GetByIdProducts/Resource",
                        "attributes": {
                          "aws:cdk:cloudformation:type": "AWS::ApiGatewayV2::Integration",
                          "aws:cdk:cloudformation:props": {
                            "apiId": {
                              "Ref": "ApiF70053CD"
                            },
                            "integrationType": "AWS_PROXY",
                            "integrationUri": {
                              "Fn::GetAtt": [
                                "getProductByIdB6983DDD",
                                "Arn"
                              ]
                            },
                            "payloadFormatVersion": "2.0"
                          }
                        },
                        "constructInfo": {
                          "fqn": "aws-cdk-lib.aws_apigatewayv2.CfnIntegration",
                          "version": "2.147.1"
                        }
                      }
                    },
                    "constructInfo": {
                      "fqn": "aws-cdk-lib.aws_apigatewayv2.HttpIntegration",
                      "version": "2.147.1"
                    }
                  },
                  "GetByIdProducts-Permission": {
                    "id": "GetByIdProducts-Permission",
                    "path": "ProductService/Api/GET--products--{id}/GetByIdProducts-Permission",
                    "attributes": {
                      "aws:cdk:cloudformation:type": "AWS::Lambda::Permission",
                      "aws:cdk:cloudformation:props": {
                        "action": "lambda:InvokeFunction",
                        "functionName": {
                          "Fn::GetAtt": [
                            "getProductByIdB6983DDD",
                            "Arn"
                          ]
                        },
                        "principal": "apigateway.amazonaws.com",
                        "sourceArn": {
                          "Fn::Join": [
                            "",
                            [
                              "arn:",
                              {
                                "Ref": "AWS::Partition"
                              },
                              ":execute-api:",
                              {
                                "Ref": "AWS::Region"
                              },
                              ":",
                              {
                                "Ref": "AWS::AccountId"
                              },
                              ":",
                              {
                                "Ref": "ApiF70053CD"
                              },
                              "/*/*/products/{id}"
                            ]
                          ]
                        }
                      }
                    },
                    "constructInfo": {
                      "fqn": "aws-cdk-lib.aws_lambda.CfnPermission",
                      "version": "2.147.1"
                    }
                  },
                  "Resource": {
                    "id": "Resource",
                    "path": "ProductService/Api/GET--products--{id}/Resource",
                    "attributes": {
                      "aws:cdk:cloudformation:type": "AWS::ApiGatewayV2::Route",
                      "aws:cdk:cloudformation:props": {
                        "apiId": {
                          "Ref": "ApiF70053CD"
                        },
                        "authorizationType": "NONE",
                        "routeKey": "GET /products/{id}",
                        "target": {
                          "Fn::Join": [
                            "",
                            [
                              "integrations/",
                              {
                                "Ref": "ApiGETproductsidGetByIdProducts477436C7"
                              }
                            ]
                          ]
                        }
                      }
                    },
                    "constructInfo": {
                      "fqn": "aws-cdk-lib.aws_apigatewayv2.CfnRoute",
                      "version": "2.147.1"
                    }
                  }
                },
                "constructInfo": {
                  "fqn": "aws-cdk-lib.aws_apigatewayv2.HttpRoute",
                  "version": "2.147.1"
                }
              },
              "POST--products": {
                "id": "POST--products",
                "path": "ProductService/Api/POST--products",
                "children": {
                  "createProduct": {
                    "id": "createProduct",
                    "path": "ProductService/Api/POST--products/createProduct",
                    "children": {
                      "Resource": {
                        "id": "Resource",
                        "path": "ProductService/Api/POST--products/createProduct/Resource",
                        "attributes": {
                          "aws:cdk:cloudformation:type": "AWS::ApiGatewayV2::Integration",
                          "aws:cdk:cloudformation:props": {
                            "apiId": {
                              "Ref": "ApiF70053CD"
                            },
                            "integrationType": "AWS_PROXY",
                            "integrationUri": {
                              "Fn::GetAtt": [
                                "createProduct6AB81851",
                                "Arn"
                              ]
                            },
                            "payloadFormatVersion": "2.0"
                          }
                        },
                        "constructInfo": {
                          "fqn": "aws-cdk-lib.aws_apigatewayv2.CfnIntegration",
                          "version": "2.147.1"
                        }
                      }
                    },
                    "constructInfo": {
                      "fqn": "aws-cdk-lib.aws_apigatewayv2.HttpIntegration",
                      "version": "2.147.1"
                    }
                  },
                  "createProduct-Permission": {
                    "id": "createProduct-Permission",
                    "path": "ProductService/Api/POST--products/createProduct-Permission",
                    "attributes": {
                      "aws:cdk:cloudformation:type": "AWS::Lambda::Permission",
                      "aws:cdk:cloudformation:props": {
                        "action": "lambda:InvokeFunction",
                        "functionName": {
                          "Fn::GetAtt": [
                            "createProduct6AB81851",
                            "Arn"
                          ]
                        },
                        "principal": "apigateway.amazonaws.com",
                        "sourceArn": {
                          "Fn::Join": [
                            "",
                            [
                              "arn:",
                              {
                                "Ref": "AWS::Partition"
                              },
                              ":execute-api:",
                              {
                                "Ref": "AWS::Region"
                              },
                              ":",
                              {
                                "Ref": "AWS::AccountId"
                              },
                              ":",
                              {
                                "Ref": "ApiF70053CD"
                              },
                              "/*/*/products"
                            ]
                          ]
                        }
                      }
                    },
                    "constructInfo": {
                      "fqn": "aws-cdk-lib.aws_lambda.CfnPermission",
                      "version": "2.147.1"
                    }
                  },
                  "Resource": {
                    "id": "Resource",
                    "path": "ProductService/Api/POST--products/Resource",
                    "attributes": {
                      "aws:cdk:cloudformation:type": "AWS::ApiGatewayV2::Route",
                      "aws:cdk:cloudformation:props": {
                        "apiId": {
                          "Ref": "ApiF70053CD"
                        },
                        "authorizationType": "NONE",
                        "routeKey": "POST /products",
                        "target": {
                          "Fn::Join": [
                            "",
                            [
                              "integrations/",
                              {
                                "Ref": "ApiPOSTproductscreateProductFFF2C1ED"
                              }
                            ]
                          ]
                        }
                      }
                    },
                    "constructInfo": {
                      "fqn": "aws-cdk-lib.aws_apigatewayv2.CfnRoute",
                      "version": "2.147.1"
                    }
                  }
                },
                "constructInfo": {
                  "fqn": "aws-cdk-lib.aws_apigatewayv2.HttpRoute",
                  "version": "2.147.1"
                }
              }
            },
            "constructInfo": {
              "fqn": "aws-cdk-lib.aws_apigatewayv2.HttpApi",
              "version": "2.147.1"
            }
          },
          "prod": {
            "id": "prod",
            "path": "ProductService/prod",
            "children": {
              "Resource": {
                "id": "Resource",
                "path": "ProductService/prod/Resource",
                "attributes": {
                  "aws:cdk:cloudformation:type": "AWS::ApiGatewayV2::Stage",
                  "aws:cdk:cloudformation:props": {
                    "apiId": {
                      "Ref": "ApiF70053CD"
                    },
                    "autoDeploy": true,
                    "stageName": "prod"
                  }
                },
                "constructInfo": {
                  "fqn": "aws-cdk-lib.aws_apigatewayv2.CfnStage",
                  "version": "2.147.1"
                }
              }
            },
            "constructInfo": {
              "fqn": "aws-cdk-lib.aws_apigatewayv2.HttpStage",
              "version": "2.147.1"
            }
          },
          "ApiUrl": {
            "id": "ApiUrl",
            "path": "ProductService/ApiUrl",
            "constructInfo": {
              "fqn": "aws-cdk-lib.CfnOutput",
              "version": "2.147.1"
            }
          },
          "CDKMetadata": {
            "id": "CDKMetadata",
            "path": "ProductService/CDKMetadata",
            "children": {
              "Default": {
                "id": "Default",
                "path": "ProductService/CDKMetadata/Default",
                "constructInfo": {
                  "fqn": "aws-cdk-lib.CfnResource",
                  "version": "2.147.1"
                }
              },
              "Condition": {
                "id": "Condition",
                "path": "ProductService/CDKMetadata/Condition",
                "constructInfo": {
                  "fqn": "aws-cdk-lib.CfnCondition",
                  "version": "2.147.1"
                }
              }
            },
            "constructInfo": {
              "fqn": "constructs.Construct",
              "version": "10.3.0"
            }
          },
          "BootstrapVersion": {
            "id": "BootstrapVersion",
            "path": "ProductService/BootstrapVersion",
            "constructInfo": {
              "fqn": "aws-cdk-lib.CfnParameter",
              "version": "2.147.1"
            }
          },
          "CheckBootstrapVersion": {
            "id": "CheckBootstrapVersion",
            "path": "ProductService/CheckBootstrapVersion",
            "constructInfo": {
              "fqn": "aws-cdk-lib.CfnRule",
              "version": "2.147.1"
            }
          }
        },
        "constructInfo": {
          "fqn": "aws-cdk-lib.Stack",
          "version": "2.147.1"
        }
      },
      "Tree": {
        "id": "Tree",
        "path": "Tree",
        "constructInfo": {
          "fqn": "constructs.Construct",
          "version": "10.3.0"
        }
      }
    },
    "constructInfo": {
      "fqn": "aws-cdk-lib.App",
      "version": "2.147.1"
    }
  }
}